{
    "CoasterBot": {
        "UserId": 282663556,
        "IconId": 137286087856104,
        "Paid": "LifeTime",
        "StartTime": "10/09/24"
    },

    "Arindo": {
        "UserId": 282663556,
        "IconId": 137286087856104,
        "Paid": "LifeTime",
        "StartTime": "10/09/24"
    },

    "FileVendor": {
        "UserId": 282663556,
        "IconId": 137286087856104,
        "Paid": "LifeTime",
        "StartTime": "10/09/24"
    },

    "UniversalDestinations": {
        "UserId": 282663556,
        "IconId": 137286087856104,
        "Paid": "LifeTime",
        "StartTime": "10/09/24"
    },

    "spector": {
        "UserId": 1546292748,
        "IconId": 137286087856104,
        "Paid": "LifeTime",
        "StartTime": "10/09/24"
    }
}